LICENSE.txt
MANIFEST.in
README.rst
setup.py
infi/__init__.py
infi.bunch.egg-info/PKG-INFO
infi.bunch.egg-info/SOURCES.txt
infi.bunch.egg-info/dependency_links.txt
infi.bunch.egg-info/namespace_packages.txt
infi.bunch.egg-info/top_level.txt
infi/bunch/__init__.py
infi/bunch/python3_compat.py
infi/bunch/test.py