Metadata-Version: 1.1
Name: infi.bunch
Version: 2.0.0
Summary: A dot-accessible dictionary (a la JavaScript objects)
Home-page: http://github.com/Infinidat/infi.bunch
Author: Rotem Yaari
Author-email: vmalloc@gmail.com
License: MIT
Keywords: bunch,dict,mapping,container,collection
Platform: UNKNOWN
Classifier: Development Status :: 5 - Production/Stable
Classifier: Intended Audience :: Developers
Classifier: Operating System :: OS Independent
Classifier: Programming Language :: Python
Classifier: Programming Language :: Python :: 2.5
Classifier: Programming Language :: Python :: 2.6
Classifier: Programming Language :: Python :: 2.7
Classifier: Topic :: Software Development
Classifier: Topic :: Software Development :: Libraries
Classifier: Topic :: Utilities
Classifier: License :: OSI Approved :: MIT License
